Metadata-Version: 1.0
Name: GaussianBinomialDistCalculator
Version: 0.1
Summary: Gaussian and Binomial Distribution Calculator
Home-page: UNKNOWN
Author: UNKNOWN
Author-email: UNKNOWN
License: UNKNOWN
Platform: UNKNOWN
